openinference/instrumentation/mcp/__init__.py
openinference/instrumentation/mcp/package.py
openinference/instrumentation/mcp/version.py
openinference_instrumentation_mcp-1.3.3.dist-info/METADATA
openinference_instrumentation_mcp-1.3.3.dist-info/WHEEL
openinference_instrumentation_mcp-1.3.3.dist-info/entry_points.txt
openinference_instrumentation_mcp-1.3.3.dist-info/licenses/LICENSE
openinference_instrumentation_mcp-1.3.3.dist-info/RECORD
