Metadata-Version: 2.4
Name: openinference-instrumentation-mcp
Version: 1.3.3
Summary: OpenInference MCP Instrumentation
Project-URL: Homepage, https://github.com/Arize-ai/openinference/tree/main/python/instrumentation/openinference-instrumentation-mcp
Author-email: OpenInference Authors <oss@arize.com>
License-Expression: Apache-2.0
License-File: LICENSE
Classifier: Development Status :: 5 - Production/Stable
Classifier: Intended Audience :: Developers
Classifier: License :: OSI Approved :: Apache Software License
Classifier: Programming Language :: Python
Classifier: Programming Language :: Python :: 3
Classifier: Programming Language :: Python :: 3.10
Classifier: Programming Language :: Python :: 3.11
Classifier: Programming Language :: Python :: 3.12
Classifier: Programming Language :: Python :: 3.13
Classifier: Programming Language :: Python :: 3.14
Requires-Python: <3.15,>=3.10
Requires-Dist: openinference-instrumentation>=0.1.27
Requires-Dist: opentelemetry-api
Requires-Dist: opentelemetry-instrumentation>=0.49b0
Requires-Dist: wrapt
Provides-Extra: instruments
Requires-Dist: mcp>=1.8.1; extra == 'instruments'
